<?xml version="1.0" encoding="UTF-8"?>
<OpenSearchDescription xmlns="http://a9.com/-/spec/opensearch/1.1/">
  <ShortName>Mohammed Aydan</ShortName>
  <Description>Search logos and developer resources on Mohammed Aydan's portfolio</Description>
  <Tags>developer portfolio logos svg png download</Tags>
  <Contact>contact@mohammed-aydan.me</Contact>
  <Url type="text/html" template="https://mohammed-aydan.me/logos?q={searchTerms}"/>
  <Url type="application/x-suggestions+json" template="https://mohammed-aydan.me/api/search-suggestions?q={searchTerms}"/>
  <Image height="64" width="64" type="image/png">https://mohammed-aydan.me/icon-192x192.png</Image>
  <Image height="16" width="16" type="image/x-icon">https://mohammed-aydan.me/favicon.ico</Image>
  <InputEncoding>UTF-8</InputEncoding>
  <SearchForm>https://mohammed-aydan.me/logos</SearchForm>
  <Language>en-us</Language>
  <Language>ar</Language>
  <OutputEncoding>UTF-8</OutputEncoding>
</OpenSearchDescription>
